setup.py
Ferris.egg-info/PKG-INFO
Ferris.egg-info/SOURCES.txt
Ferris.egg-info/dependency_links.txt
Ferris.egg-info/top_level.txt
ferris3/__init__.py
ferris3/anodi.py
ferris3/caching.py
ferris3/chain.py
ferris3/discovery.py
ferris3/endpoints.py
ferris3/endpoints_apis.py
ferris3/google_apis.py
ferris3/hvild.py
ferris3/messages.py
ferris3/ndb.py
ferris3/oauth2.py
ferris3/retries.py
ferris3/search.py
ferris3/settings.py
ferris3/template.py
ferris3/tool_chain.py